__init__.py
api.py
database.py
models.py
controllers/__init__.py
controllers/docker.py
controllers/health_check.py
controllers/ip.py
js_api-0.2.40.dist-info/licenses/LICENSE
util/__init__.py
util/auth.py
util/docker.py
util/healthcheck.py
util/logging.py
js_api-0.2.40.dist-info/METADATA
js_api-0.2.40.dist-info/WHEEL
js_api-0.2.40.dist-info/top_level.txt
js_api-0.2.40.dist-info/RECORD
