Metadata-Version: 2.4
Name: js-api
Version: 0.2.40
Summary: Custom API written in Python using FastAPI
Author-email: Jack Stockley <jack@jstockley.com>
Project-URL: Homepage, https://github.com/jnstockley/api
Project-URL: Repository, https://github.com/jnstockley/api.git
Project-URL: Issues, https://github.com/jnstockley/api/issues
Keywords: starter,template,python
Classifier: Programming Language :: Python :: 3
Requires-Python: <4.0,>=3.13
License-File: LICENSE
Requires-Dist: fastapi[standard]==0.128.0
Requires-Dist: psycopg==3.3.2
Requires-Dist: psycopg-binary==3.3.2
Requires-Dist: sqlalchemy==2.0.45
Requires-Dist: sqlmodel==0.0.31
Requires-Dist: python-dotenv==1.2.1
Dynamic: license-file
